README.md
setup.py
apiato/__init__.py
apiato/config.py
apiato.egg-info/PKG-INFO
apiato.egg-info/SOURCES.txt
apiato.egg-info/dependency_links.txt
apiato.egg-info/requires.txt
apiato.egg-info/top_level.txt
apiato/api/__init__.py
apiato/api/api.py
apiato/api/attribute.py
apiato/api/auth.py
apiato/api/base.py
apiato/api/cluster.py
apiato/api/fim.py
apiato/api/functionalalias.py
apiato/api/host.py
apiato/api/hostaliases.py
apiato/api/instance.py
apiato/api/job.py
apiato/api/metadata.py
apiato/api/rundeck.py
apiato/api/type.py
apiato/api/volume.py
apiato/tests/__init__.py
apiato/tests/attribute_test.py
apiato/tests/auth_test.py
apiato/tests/cluster_test.py
apiato/tests/config_test.py
apiato/tests/functionalalias_test.py
apiato/tests/host_test.py
apiato/tests/instance_test.py
apiato/tests/job_test.py
apiato/tests/metadata_test.py
apiato/tests/rundeck_test.py
apiato/tests/volume_test.py
bin/apiato