Metadata-Version: 1.0
Name: apiato
Version: 0.9.7
Summary: CERN Apiato REST API
Home-page: https://github.com/cerndb/dbod-api
Author: Ignacio Coterillo
Author-email: icot@cern.ch
License: GPLv3
Platform: UNKNOWN
